ribin_common/__init__.py
ribin_common/generator.py
ribin_common/logger.py
ribin_common/md5.py
ribin_common/signal_handler.py
ribin_common/singleton.py
ribin_common/timer.py
ribin_common-1.0.0.dist-info/LICENSE
ribin_common-1.0.0.dist-info/METADATA
ribin_common-1.0.0.dist-info/WHEEL
ribin_common-1.0.0.dist-info/top_level.txt
ribin_common-1.0.0.dist-info/RECORD
