Metadata-Version: 2.1
Name: ribin-common
Version: 1.0.0
Summary: A common lib for ribin
Author: RibinCao
Author-email: ribincao@gmail.com
License-File: LICENSE
